{
    "name": "Algo_MenMount_Dev_Container",
    "image": "mcr.microsoft.com/vscode/devcontainers/base:debian",
    "build": {
        "dockerfile": "Dockerfile"
    },
    "settings": {
        "terminal.integrated.shell.linux": "/bin/bash"
    },
    "extensions": [
        "ms-python.python",
        "ms-azuretools.vscode-docker"
    ],
    "postCreateCommand": "algokit localnet start",
    "remoteUser": "root",
    "features": {
        "docker-in-docker": "latest"
    },
    "mounts": [
        "source=/var/run/docker.sock,target=/var/run/docker.sock,type=bind"
    ]
}
